LICENSE
MANIFEST.in
README.md
setup.py
iblviewer/__init__.py
iblviewer/application.py
iblviewer/collection.py
iblviewer/launcher.py
iblviewer/mouse_brain.py
iblviewer/objects.py
iblviewer/qt_application.py
iblviewer/utils.py
iblviewer/volume.py
iblviewer.egg-info/PKG-INFO
iblviewer.egg-info/SOURCES.txt
iblviewer.egg-info/dependency_links.txt
iblviewer.egg-info/entry_points.txt
iblviewer.egg-info/requires.txt
iblviewer.egg-info/top_level.txt
iblviewer_examples/__init__.py
iblviewer_examples/headless_render.py
iblviewer_examples/human_brain.py
iblviewer_examples/ibl_brain_coverage.py
iblviewer_examples/ibl_brain_wide_map.py
iblviewer_examples/ibl_insertion_probes.py
iblviewer_examples/ibl_point_neurons.py
iblviewer_examples/ibl_volume_mapping.py
iblviewer_examples/viewer.ipynb
iblviewer_examples/data/channels.f22c0fd9-6b7d-f8dd-9229-884c6f573046.pqt
iblviewer_examples/data/exp2_db4df448-e449-4a6f-a0e7-288711e7a75a_both
iblviewer_examples/data/exp3_3dd347df-f14e-40d5-9ff2-9c49f84d2157_both
iblviewer_examples/data/exp4_3c851386-e92d-4533-8d55-89a46f0e7384_both
iblviewer_examples/data/exp5_158d5d35-a2ab-4a76-87b0-51048c5d5283_both
iblviewer_examples/data/ibl_point_neurons.npz
iblviewer_examples/data/ncov_100.npz
iblviewer_examples/data/ncov_25.npz
iblviewer_examples/data/ncov_50.npz
iblviewer_examples/data/stimonR_top10_rawpoints.p
iblviewer_examples/data/valid_insertions.p
iblviewer_examples/data/valid_insertions_data.p