Metadata-Version: 2.1
Name: iblviewer
Version: 2.4.6
Summary: An interactive GPU-accelerated 3D viewer based on VTK
Home-page: https://github.com/int-brain-lab/iblviewer
Author: Nicolas Antille
Author-email: nicolas.antille@gmail.com
License: MIT
Platform: UNKNOWN
Classifier: Development Status :: 5 - Production/Stable
Classifier: Intended Audience :: Science/Research
Classifier: License :: OSI Approved :: MIT License
Classifier: Operating System :: POSIX :: Linux
Classifier: Operating System :: MacOS
Classifier: Programming Language :: Python :: 3.8
License-File: LICENSE
